{
    "name": "Dr. Sachin Dhama",
    "qualification": "M.A., B.Ed., Ph.D.",
    "experience": "25+ Years in Education",
    "message": "Dear Students, Parents, and Well-Wishers,\r\n\r\nIt gives me immense pleasure to welcome you to Nav Jeevan Public School \u2014 a place where learning is a lifelong journey filled with discovery, growth, and inspiration.\r\n\r\nAt our school, we aim to create an environment where each child feels valued, encouraged, and empowered to reach their highest potential. Education here is not confined to textbooks and classrooms; it extends to building character, integrity, and compassion.\r\n\r\nOur team of dedicated teachers works tirelessly to make learning meaningful and engaging. We emphasize not only academic excellence but also sports, arts, and co-curricular activities that shape a child\u2019s personality in a balanced way.\r\n\r\nAs Principal, I believe that the partnership between the school and parents is crucial for a child\u2019s development. Together, let us inspire our students to become lifelong learners and responsible global citizens.",
    "photo": "uploads\/principal_photo.jpeg"
}